ncbi_refseq_accession_db/__init__.py
ncbi_refseq_accession_db/db.marisa
ncbi_refseq_accession_db/version.py
ncbi_refseq_accession_db-2024.9.7.dist-info/METADATA
ncbi_refseq_accession_db-2024.9.7.dist-info/WHEEL
ncbi_refseq_accession_db-2024.9.7.dist-info/top_level.txt
ncbi_refseq_accession_db-2024.9.7.dist-info/RECORD
